__init__.pyi
adcfft/__init__.pyi
automation/__init__.pyi
badger2040/__init__.pyi
breakout_as7262/__init__.pyi
breakout_bh1745/__init__.pyi
breakout_bme280/__init__.pyi
breakout_bme68x/__init__.pyi
breakout_bmp280/__init__.pyi
breakout_dotmatrix/__init__.pyi
breakout_encoder/__init__.pyi
breakout_encoder_wheel/__init__.pyi
breakout_icp10125/__init__.pyi
breakout_ioexpander/__init__.pyi
breakout_ltr559/__init__.pyi
breakout_matrix11x7/__init__.pyi
breakout_mics6814/__init__.pyi
breakout_mlx90640/__init__.pyi
breakout_msa301/__init__.pyi
breakout_paa5100/__init__.pyi
breakout_pmw3901/__init__.pyi
breakout_potentiometer/__init__.pyi
breakout_rgbmatrix5x5/__init__.pyi
breakout_rtc/__init__.pyi
breakout_scd41/__init__.pyi
breakout_sgp30/__init__.pyi
breakout_trackball/__init__.pyi
breakout_vl53l5cx/__init__.pyi
cosmic/__init__.pyi
cppmem/__init__.pyi
encoder/__init__.pyi
galactic/__init__.pyi
gfx_pack/__init__.pyi
hub75/__init__.pyi
inky_frame/__init__.pyi
interstate75/__init__.pyi
inventor/__init__.pyi
jpegdec/__init__.pyi
motor/__init__.pyi
motor/motor2040.pyi
motor/pico_motor_shim.pyi
pcf85063a/__init__.pyi
picoexplorer/__init__.pyi
picographics/__init__.pyi
picokeypad/__init__.pyi
picoscroll/__init__.pyi
picosynth/__init__.pyi
picounicorn/__init__.pyi
picovector/__init__.pyi
picovision/__init__.pyi
picowireless/__init__.pyi
pimoroni/__init__.pyi
pimoroni_bus/__init__.pyi
pimoroni_i2c/__init__.pyi
plasma/__init__.pyi
plasma/plasma2040.pyi
plasma/plasma_stick.pyi
pms5003/__init__.pyi
pngdec/__init__.pyi
qrcode/__init__.pyi
servo/__init__.pyi
servo/servo2040.pyi
stellar/__init__.pyi
tca/__init__.pyi
wakeup/__init__.pyi
north101_pimoroni_pico_stubs-1.23.0.dist-info/METADATA
north101_pimoroni_pico_stubs-1.23.0.dist-info/WHEEL
north101_pimoroni_pico_stubs-1.23.0.dist-info/RECORD
