Metadata-Version: 2.1
Name: north101-pimoroni-pico-stubs
Version: 1.23.0
Summary: Micropython Stubs for Pimoroni MicroPython libraries for RP2040-based boards
Home-page: https://github.com/pimoroni/pimoroni-pico-stubs
License: MIT
Requires-Python: >=3.10,<4.0
Classifier: License :: OSI Approved :: MIT License
Classifier: Programming Language :: Python :: 3
Classifier: Programming Language :: Python :: 3.10
Classifier: Programming Language :: Python :: 3.11
Classifier: Programming Language :: Python :: 3.12
Requires-Dist: micropython-rp2-rpi_pico_w-stubs (>=1.23.0)
Project-URL: Repository, https://github.com/pimoroni/pimoroni-pico-stubs
